{
	"pools": [
		{
			"rolls": 1,
			"entries": [
				{
					"type": "minecraft:item",
					"name": "minecraft:item_frame",
					"functions": [
						{
							"function": "minecraft:set_components",
							"components": {
								"minecraft:custom_data": {
									"iyc": {"iron_ladder": true},
									"smithed": {"ignore": {"functionality": true,"crafting": true}}
								},
								"minecraft:item_name": "[{\"translate\":\"iyc.iron_ladder\",\"italic\":false,\"color\":\"white\"}]",
								"minecraft:lore": [
									"[{\"translate\":\"iyc.imagineyourcraft\",\"italic\":true,\"color\":\"blue\"}]"
								],
								"minecraft:custom_model_data": 2015099
							}
						}
					]
				}
			]
		}
	]
}

